nbtools/__init__.py
nbtools/_frontend.py
nbtools/_version.py
nbtools/basewidget.py
nbtools/event_manager.py
nbtools/form.py
nbtools/nbtools.json
nbtools/parsing_manager.py
nbtools/settings.py
nbtools/tool_manager.py
nbtools/uibuilder.py
nbtools/uioutput.py
nbtools/utils.py
nbtools/labextension/build_log.json
nbtools/labextension/package.json
nbtools/labextension/schemas/@g2nb/nbtools/package.json.orig
nbtools/labextension/schemas/@g2nb/nbtools/plugin.json
nbtools/labextension/static/7f7e8263c4c886d64552d3e7dfc0304ed4a56a3636b7f68b95ba1c6be60d1f43.png
nbtools/labextension/static/lib_index_js.6e76e18ed67ea06d56a0.js
nbtools/labextension/static/lib_index_js.6e76e18ed67ea06d56a0.js.map
nbtools/labextension/static/lib_plugin_js.3d6a69190252a9993d8d.js
nbtools/labextension/static/lib_plugin_js.3d6a69190252a9993d8d.js.map
nbtools/labextension/static/lib_registry_js-lib_uibuilder_js-lib_uioutput_js.019344813cdd5177370d.js
nbtools/labextension/static/lib_registry_js-lib_uibuilder_js-lib_uioutput_js.019344813cdd5177370d.js.map
nbtools/labextension/static/node_modules_css-loader_dist_cjs_js_style_basewidget_css-node_modules_css-loader_dist_cjs_js_-b1a354.e63871dc8f89e0b8fe37.js
nbtools/labextension/static/node_modules_css-loader_dist_cjs_js_style_basewidget_css-node_modules_css-loader_dist_cjs_js_-b1a354.e63871dc8f89e0b8fe37.js.map
nbtools/labextension/static/remoteEntry.cfaacf54be78eb3cc104.js
nbtools/labextension/static/remoteEntry.cfaacf54be78eb3cc104.js.map
nbtools/labextension/static/style.js
nbtools/labextension/static/style_index_js.c993bb57d60349fb7c52.js
nbtools/labextension/static/style_index_js.c993bb57d60349fb7c52.js.map
nbtools/labextension/static/vendors-node_modules_css-loader_dist_runtime_api_js-node_modules_css-loader_dist_runtime_cssW-72eba1.ac7c019ff2b64af24899.js
nbtools/labextension/static/vendors-node_modules_css-loader_dist_runtime_api_js-node_modules_css-loader_dist_runtime_cssW-72eba1.ac7c019ff2b64af24899.js.map
nbtools/nbextension/__init__.py
nbtools-24.8.0.dist-info/METADATA
nbtools-24.8.0.dist-info/WHEEL
nbtools-24.8.0.dist-info/licenses/LICENSE.txt
nbtools-24.8.0.dist-info/RECORD
