Metadata-Version: 2.3
Name: nbtools
Version: 24.8.0
Summary: Framework for creating user-friendly Jupyter notebooks, accessible to both programming and non-programming users alike.
Project-URL: Homepage, https://github.com/g2nb/nbtools
Author-email: Thorin Tabor <tmtabor@cloud.ucsd.edu>
License: BSD 3-Clause License
License-File: LICENSE.txt
Keywords: Jupyter,JupyterLab,JupyterLab3
Classifier: Framework :: Jupyter
Classifier: Intended Audience :: Developers
Classifier: Intended Audience :: Science/Research
Classifier: License :: OSI Approved :: BSD License
Classifier: Programming Language :: Python
Classifier: Programming Language :: Python :: 3
Classifier: Programming Language :: Python :: 3.6
Classifier: Programming Language :: Python :: 3.7
Classifier: Programming Language :: Python :: 3.8
Classifier: Programming Language :: Python :: 3.9
Requires-Python: >=3.6
Requires-Dist: ipyuploads
Requires-Dist: ipywidgets<9,>7
Requires-Dist: jupyterlab<4,>=3.4
